{
    "assemble_plate":
    {
        "x":-0.01911,
        "y":0.3755,
        "z":0.186,
        "roll":0,
        "pitch":0,
        "yaw":0.00625,
        "width":32,
        "height":32
    },
    "storage_plate":
    {
        "x":-0.01911,
        "y":0.3755,
        "z":0.186,
        "roll":0,
        "pitch":0,
        "yaw":0.00625,
        "width":32,
        "height":32
    },
    "b9_1":
    {
        "x":5,
        "y":7,
        "z":4,
        "ori":0
    },
    "b9_2":
    {
        "x":8,
        "y":17,
        "z":5,
        "ori":0
    },
    "b9_3":
    {
        "x":5,
        "y":5,
        "z":1,
        "ori":0
    },
    "b9_4":
    {
        "x":5,
        "y":9,
        "z":1,
        "ori":0
    },
    "b2_1":
    {
        "x":7,
        "y":16,
        "z":4,
        "ori":0
    },
    "b5_1":
    {
        "x":5,
        "y":6,
        "z":2,
        "ori":0
    },
    "b5_2":
    {
        "x":6,
        "y":16,
        "z":3,
        "ori":1
    },
    "b5_3":
    {
        "x":6,
        "y":19,
        "z":3,
        "ori":1
    },
    "b6_1":
    {
        "x":5,
        "y":5,
        "z":3,
        "ori":0
    },
    "b6_2":
    {
        "x":9,
        "y":15,
        "z":2,
        "ori":0
    },
    "b6_3":
    {
        "x":6,
        "y":15,
        "z":2,
        "ori":0
    },
    "b3_1":
    {
        "x":5,
        "y":15,
        "z":1,
        "ori":1
    },
    "b3_2":
    {
        "x":5,
        "y":19,
        "z":1,
        "ori":1
    }
}
